TraceManager/__init__.py
TraceManager-0.0.1.dist-info/LICENSE
TraceManager-0.0.1.dist-info/METADATA
TraceManager-0.0.1.dist-info/WHEEL
TraceManager-0.0.1.dist-info/top_level.txt
TraceManager-0.0.1.dist-info/RECORD
